stockanalysis_scraper/__init__.py
stockanalysis_scraper/config.ini
stockanalysis_scraper/scraper/__init__.py
stockanalysis_scraper/scraper/config.py
stockanalysis_scraper/scraper/enums.py
stockanalysis_scraper/scraper/scraper.py
stockanalysis_scraper/scraper/urls.py
stockanalysis_scraper/tests/__init__.py
stockanalysis_scraper/tests/test_scraper.py
stockanalysis_scraper-1.0.1.dist-info/LICENSE
stockanalysis_scraper-1.0.1.dist-info/METADATA
stockanalysis_scraper-1.0.1.dist-info/WHEEL
stockanalysis_scraper-1.0.1.dist-info/top_level.txt
stockanalysis_scraper-1.0.1.dist-info/RECORD
