Metadata-Version: 2.1
Name: stockanalysis-scraper
Version: 1.0.1
Summary: A web scraper for different market data and news from https://stockanalysis.com/
Home-page: https://github.com/darkshloser/stockanalysis-scraper
Author: Dobromir Kovachev
Author-email: dobromir.mail@gmail.com
Classifier: Programming Language :: Python :: 3
Classifier: License :: OSI Approved :: MIT License
Classifier: Operating System :: OS Independent
Requires-Python: >=3.6
License-File: LICENSE
Requires-Dist: beautifulsoup4
Requires-Dist: requests
Requires-Dist: selenium
Requires-Dist: webdriver-manager
